CHANGES.txt
DEPENDENCES.txt
README.txt
setup.py
src/ng/__init__.py
src/ng.site.addon.remotefs.egg-info/PKG-INFO
src/ng.site.addon.remotefs.egg-info/SOURCES.txt
src/ng.site.addon.remotefs.egg-info/dependency_links.txt
src/ng.site.addon.remotefs.egg-info/namespace_packages.txt
src/ng.site.addon.remotefs.egg-info/not-zip-safe
src/ng.site.addon.remotefs.egg-info/requires.txt
src/ng.site.addon.remotefs.egg-info/top_level.txt
src/ng/site/__init__.py
src/ng/site/addon/__init__.py
src/ng/site/addon/remotefs/__init__.py
src/ng/site/addon/remotefs/configure.zcml
src/ng/site/addon/remotefs/ng.site.addon.remotefs.txt
src/ng/site/addon/remotefs/adapter/__init__.py
src/ng/site/addon/remotefs/adapter/configure.zcml
src/ng/site/addon/remotefs/adapter/remoteobject2titlesubscriber.py
src/ng/site/addon/remotefs/annotation/__init__.py
src/ng/site/addon/remotefs/annotation/configure.zcml
src/ng/site/addon/remotefs/annotationswitcher/__init__.py
src/ng/site/addon/remotefs/annotationswitcher/configure.zcml
src/ng/site/addon/remotefs/contain/__init__.py
src/ng/site/addon/remotefs/contain/configure.zcml
src/ng/site/addon/remotefs/convert/__init__.py
src/ng/site/addon/remotefs/convert/configure.zcml
src/ng/site/addon/remotefs/etc/ng.site.addon.remotefs-configure.zcml
src/ng/site/addon/remotefs/fuzzytraverser/__init__.py
src/ng/site/addon/remotefs/fuzzytraverser/configure.zcml
src/ng/site/addon/remotefs/install/__init__.py
src/ng/site/addon/remotefs/install/configure.zcml
src/ng/site/addon/remotefs/install/install_content.py
src/ng/site/addon/remotefs/install/install_converter.py
src/ng/site/addon/remotefs/install/install_index.py
src/ng/site/addon/remotefs/rss/__init__.py
src/ng/site/addon/remotefs/rss/configure.zcml
src/ng/site/addon/remotefs/search/__init__.py
src/ng/site/addon/remotefs/search/configure.zcml